package_rodrigo/__init__.py
package_rodrigo/file2_name.py
package_rodrigo/processador.py.py
imagem_processador_rodrigo-0.0.1.dist-info/METADATA
imagem_processador_rodrigo-0.0.1.dist-info/WHEEL
imagem_processador_rodrigo-0.0.1.dist-info/top_level.txt
imagem_processador_rodrigo-0.0.1.dist-info/RECORD
