Metadata-Version: 2.1
Name: imagem_processador_rodrigo
Version: 0.0.1
Summary: Pacote para processamento de imagens
Home-page: https://github.com/rodrigopinheiro1996/pacote-processamento-python
Author: rodrigo
Author-email: rodrigopinheirotm@gmail.com
Requires-Python: >=3.8
Requires-Dist: Pillow==8.3.1
Requires-Dist: numpy==1.21.1
